optional_imports/__init__.py
optional_imports/_version.py
optional_imports/opt_imports.py
optional_imports-1.0.4.dist-info/LICENSE
optional_imports-1.0.4.dist-info/METADATA
optional_imports-1.0.4.dist-info/WHEEL
optional_imports-1.0.4.dist-info/top_level.txt
optional_imports-1.0.4.dist-info/RECORD
